{
  "kind": "collectionType",
  "collectionName": "projects",
  "info": {
    "name": "projects",
    "description": ""
  },
  "options": {
    "increments": true,
    "timestamps": true,
    "draftAndPublish": true
  },
  "attributes": {
    "title": {
      "type": "string"
    },
    "media": {
      "collection": "file",
      "via": "related",
      "allowedTypes": [
        "images",
        "files",
        "videos"
      ],
      "plugin": "upload",
      "required": false
    },
    "description": {
      "type": "text"
    },
    "slug": {
      "type": "string"
    }
  }
}
